src/__init__.py
src/camera.py
src/templates/index.html
src/xml/haarcascade_frontalface_dataset.xml
zhengen_src-1.0.0.data/data/haarcascade_frontalface_dataset.xml
zhengen_src-1.0.0.data/data/index.html
zhengen_src-1.0.0.dist-info/DESCRIPTION.rst
zhengen_src-1.0.0.dist-info/METADATA
zhengen_src-1.0.0.dist-info/RECORD
zhengen_src-1.0.0.dist-info/WHEEL
zhengen_src-1.0.0.dist-info/metadata.json
zhengen_src-1.0.0.dist-info/top_level.txt
